tessie_relay/__init__.py
tessie_relay/helpers.py
tessie_relay/payload_types.py
tessie_relay/psi_coldbox.py
tessie_relay/relay.py
tessie_relay-0.3.0.dist-info/METADATA
tessie_relay-0.3.0.dist-info/WHEEL
tessie_relay-0.3.0.dist-info/RECORD
