Metadata-Version: 2.4
Name: tessie_relay
Version: 0.3.0
Summary: Relay and control for tessie
Project-URL: Homepage, https://gitlab.cern.ch/psi/tessie-relay
Classifier: Development Status :: 4 - Beta
Classifier: License :: OSI Approved :: BSD License
Classifier: Programming Language :: Python :: 3 :: Only
Classifier: Programming Language :: Python :: 3.9
Classifier: Programming Language :: Python :: 3.10
Classifier: Programming Language :: Python :: 3.11
Classifier: Programming Language :: Python :: 3.12
Classifier: Programming Language :: Python :: 3.13
Classifier: Topic :: Scientific/Engineering :: Physics
Requires-Python: >=3.9
Requires-Dist: paho-mqtt>=2.1.0
Requires-Dist: questdb>=2.0.3
